ExampleFiles/__init__.py
ExampleFiles/test_10.py
ExampleFiles/test_11.py
ExampleFiles/test_2.py
ExampleFiles/test_3.py
ExampleFiles/test_4.py
ExampleFiles/test_5.py
ExampleFiles/test_6.py
ExampleFiles/test_8.py
ExampleFiles/test_9.py
UnitTesterSG/LICENSE.txt
UnitTesterSG/MANUAL.txt
UnitTesterSG/UnitTesterSGFunctions.py
UnitTesterSG/__init__.py
UnitTesterSG/__main__.py
UnitTesterSG/nestedObjectsFunctions.py
UnitTesterSG/pytestDriver.py
UnitTesterSG-6.2.2.data/data/LICENSE.txt
UnitTesterSG-6.2.2.data/data/MANUAL.txt
test12/__init__.py
test12/test_12.py
UnitTesterSG-6.2.2.dist-info/METADATA
UnitTesterSG-6.2.2.dist-info/WHEEL
UnitTesterSG-6.2.2.dist-info/top_level.txt
UnitTesterSG-6.2.2.dist-info/RECORD
