Metadata-Version: 2.1
Name: UnitTesterSG
Version: 6.2.2
Summary: UnitTesterSG is for unit testing scientific/engineering outputs. It accommodates nested and even staggered array type structures, and mixed data types (like strings and integers etc). It also enables you to set numerical and absolute tolerances.
Home-page: https://github.com/AdityaSavara/UnitTesterSG
Author: Aditya Savara
Author-email: AditySavara2008@u.northwestern.edu
License: BSD-3-Clause
Platform: UNKNOWN
Classifier: License :: OSI Approved :: BSD License
Classifier: Programming Language :: Python
Classifier: Programming Language :: Python :: 3
Classifier: Programming Language :: Python :: 3.6
Classifier: Programming Language :: Python :: Implementation :: CPython
Classifier: Programming Language :: Python :: Implementation :: PyPy
Requires-Python: >=3.0.0
Requires-Dist: numpy
Provides-Extra: complete
Requires-Dist: colorama ; extra == 'complete'
Requires-Dist: pytest ; extra == 'complete'
